LICENSE
MANIFEST.in
README.md
setup.cfg
setup.py
p.url.egg-info/PKG-INFO
p.url.egg-info/SOURCES.txt
p.url.egg-info/dependency_links.txt
p.url.egg-info/requires.txt
p.url.egg-info/top_level.txt
purl/__init__.py
purl/exceptions.py