Metadata-Version: 1.1
Name: p.url
Version: 0.1.0a4
Summary: A simple url parsing library for python
Home-page: https://github.com/ultrabluewolf/p.url
Author: Britney L.
Author-email: UNKNOWN
License: MIT
Keywords: url
Platform: UNKNOWN
Classifier: Development Status :: 3 - Alpha
Classifier: Intended Audience :: Developers
Classifier: Topic :: Software Development :: Libraries :: Python Modules
Classifier: License :: OSI Approved :: MIT License
Classifier: Programming Language :: Python :: 2
Classifier: Programming Language :: Python :: 2.7
Classifier: Programming Language :: Python :: 3
Classifier: Programming Language :: Python :: 3.5
